dl_plus/__main__.py
dl_plus/backend.py
dl_plus/config.py
dl_plus/const.py
dl_plus/core.py
dl_plus/deprecated.py
dl_plus/exceptions.py
dl_plus/pypi.py
dl_plus/utils.py
dl_plus/ytdl.py
dl_plus/cli/__init__.py
dl_plus/cli/args.py
dl_plus/cli/cli.py
dl_plus/cli/command.py
dl_plus/cli/commands/__init__.py
dl_plus/cli/commands/base.py
dl_plus/cli/commands/backend/__init__.py
dl_plus/cli/commands/backend/base.py
dl_plus/cli/commands/backend/info.py
dl_plus/cli/commands/backend/install.py
dl_plus/cli/commands/backend/list.py
dl_plus/cli/commands/backend/uninstall.py
dl_plus/cli/commands/backend/update.py
dl_plus/cli/commands/config/__init__.py
dl_plus/cli/commands/config/show/__init__.py
dl_plus/cli/commands/config/show/backends.py
dl_plus/cli/commands/config/show/main.py
dl_plus/cli/commands/extractor/__init__.py
dl_plus/cli/commands/extractor/base.py
dl_plus/cli/commands/extractor/install.py
dl_plus/cli/commands/extractor/list.py
dl_plus/cli/commands/extractor/uninstall.py
dl_plus/cli/commands/extractor/update.py
dl_plus/extractor/__init__.py
dl_plus/extractor/extractor.py
dl_plus/extractor/machinery.py
dl_plus/extractor/peqn.py
dl_plus/extractor/plugin.py
dl_plus-0.10.1.dist-info/licenses/LICENSE
dl_plus-0.10.1.dist-info/METADATA
dl_plus-0.10.1.dist-info/WHEEL
dl_plus-0.10.1.dist-info/entry_points.txt
dl_plus-0.10.1.dist-info/top_level.txt
dl_plus-0.10.1.dist-info/RECORD
