Metadata-Version: 2.4
Name: dl-plus
Version: 0.10.1
Summary: A youtube-dl extension with pluggable extractors
Author-email: Dmitry Meyer <me@undef.im>
License: MIT
Project-URL: Homepage, https://github.com/un-def/dl-plus
Project-URL: Repository, https://github.com/un-def/dl-plus.git
Project-URL: Changelog, https://github.com/un-def/dl-plus/blob/master/CHANGELOG.md
Project-URL: Issues, https://github.com/un-def/dl-plus/issues
Classifier: Development Status :: 4 - Beta
Classifier: License :: OSI Approved :: MIT License
Classifier: Programming Language :: Python :: 3
Classifier: Programming Language :: Python :: 3.9
Classifier: Programming Language :: Python :: 3.10
Classifier: Programming Language :: Python :: 3.11
Classifier: Programming Language :: Python :: 3.12
Classifier: Programming Language :: Python :: 3.13
Requires-Python: >=3.9
License-File: LICENSE
Dynamic: license-file
